graph_transformer/__init__.py
graph_transformer/graph_transformer_model.py
graph_transformer-0.2.1.dist-info/LICENSE.txt
graph_transformer-0.2.1.dist-info/METADATA
graph_transformer-0.2.1.dist-info/WHEEL
graph_transformer-0.2.1.dist-info/top_level.txt
graph_transformer-0.2.1.dist-info/RECORD
